cyberfusion/QueueSupport/__init__.py
cyberfusion/QueueSupport/database.py
cyberfusion/QueueSupport/encoders.py
cyberfusion/QueueSupport/enums.py
cyberfusion/QueueSupport/interfaces.py
cyberfusion/QueueSupport/outcomes.py
cyberfusion/QueueSupport/sentinels.py
cyberfusion/QueueSupport/settings.py
cyberfusion/QueueSupport/utilities.py
cyberfusion/QueueSupport/exceptions/__init__.py
cyberfusion/QueueSupport/items/__init__.py
cyberfusion/QueueSupport/items/chmod.py
cyberfusion/QueueSupport/items/chown.py
cyberfusion/QueueSupport/items/command.py
cyberfusion/QueueSupport/items/copy.py
cyberfusion/QueueSupport/items/database_create.py
cyberfusion/QueueSupport/items/database_drop.py
cyberfusion/QueueSupport/items/database_user_drop.py
cyberfusion/QueueSupport/items/database_user_ensure_state.py
cyberfusion/QueueSupport/items/database_user_grant_grant.py
cyberfusion/QueueSupport/items/database_user_grant_revoke.py
cyberfusion/QueueSupport/items/mkdir.py
cyberfusion/QueueSupport/items/move.py
cyberfusion/QueueSupport/items/rmtree.py
cyberfusion/QueueSupport/items/systemd_daemon_reload.py
cyberfusion/QueueSupport/items/systemd_tmp_files_create.py
cyberfusion/QueueSupport/items/systemd_unit_disable.py
cyberfusion/QueueSupport/items/systemd_unit_enable.py
cyberfusion/QueueSupport/items/systemd_unit_reload.py
cyberfusion/QueueSupport/items/systemd_unit_restart.py
cyberfusion/QueueSupport/items/systemd_unit_start.py
cyberfusion/QueueSupport/items/systemd_unit_stop.py
cyberfusion/QueueSupport/items/unlink.py
cyberfusion/QueueSupport/migrations/__init__.py
cyberfusion/QueueSupport/migrations/env.py
cyberfusion/QueueSupport/migrations/versions/03d4e411c575_add_fail_silently.py
cyberfusion/QueueSupport/migrations/versions/2f4316506856_add_cascade_deletes.py
cyberfusion/QueueSupport/migrations/versions/52d1b17abcd0_add_status.py
cyberfusion/QueueSupport/migrations/versions/571e55ab5ed5_initial_migration.py
python3_cyberfusion_queue_support-3.3.2.dist-info/METADATA
python3_cyberfusion_queue_support-3.3.2.dist-info/WHEEL
python3_cyberfusion_queue_support-3.3.2.dist-info/entry_points.txt
python3_cyberfusion_queue_support-3.3.2.dist-info/top_level.txt
python3_cyberfusion_queue_support-3.3.2.dist-info/RECORD
