Metadata-Version: 2.4
Name: python3-cyberfusion-queue-support
Version: 3.3.2
Summary: Library to queue actions.
Author-email: Cyberfusion <support@cyberfusion.io>
Project-URL: Source, https://github.com/CyberfusionIO/python3-cyberfusion-queue-support
Requires-Dist: python3-cyberfusion-systemd-support~=2.2
Requires-Dist: python3-cyberfusion-database-support~=3.2
Requires-Dist: alembic==1.13.2
Requires-Dist: SQLAlchemy==2.0.40
Requires-Dist: pydantic-settings==2.8.1
